setup.py
django_hash_filter/__init__.py
django_hash_filter/models.py
django_hash_filter/tests.py
django_hash_filter.egg-info/PKG-INFO
django_hash_filter.egg-info/SOURCES.txt
django_hash_filter.egg-info/dependency_links.txt
django_hash_filter.egg-info/not-zip-safe
django_hash_filter.egg-info/requires.txt
django_hash_filter.egg-info/top_level.txt
django_hash_filter/templatetags/__init__.py
django_hash_filter/templatetags/hash_filter.py